modep_client/__init__.py
modep_client/modep_client.py
modep_client-0.0.1.dist-info/AUTHORS.rst
modep_client-0.0.1.dist-info/LICENSE
modep_client-0.0.1.dist-info/METADATA
modep_client-0.0.1.dist-info/WHEEL
modep_client-0.0.1.dist-info/top_level.txt
modep_client-0.0.1.dist-info/RECORD
