Metadata-Version: 2.1
Name: modep-client
Version: 0.0.1
Summary: Python client for the modep API
Home-page: https://github.com/modep-ai/modep-client
Author: modep-ai
Author-email: contact@modep.ai
License: MIT license
Keywords: modep_client
Platform: UNKNOWN
Classifier: Development Status :: 2 - Pre-Alpha
Classifier: Intended Audience :: Developers
Classifier: License :: OSI Approved :: MIT License
Classifier: Natural Language :: English
Classifier: Programming Language :: Python :: 3
Classifier: Programming Language :: Python :: 3.6
Classifier: Programming Language :: Python :: 3.7
Classifier: Programming Language :: Python :: 3.8
Requires-Python: >=3.6
Requires-Dist: pandas (==1.2.4)
Requires-Dist: requests (==2.25.1)
Requires-Dist: requests-toolbelt (==0.9.1)
